{
    "required": true,
    "minVersion": "0.8",
    "package": "de.pfannekuchen.lotas.mixin",
    "compatibilityLevel": "JAVA_8",
    "mixins": [
    	
    ],
    "client": [
    	"MixinMinecraftClient",
    	"MixinMinecraftServer",
    	"accessors.AccessorMinecraftClient",
    	"accessors.AccessorTimer",
    	"accessors.AccessorTextFieldWidget",
    	"accessors.AccessorCreateWorldScreen",
    	"accessors.AccessorServerPlayerEntity",
    	"render.binds.MixinTickrateChangerAchievement",
		"render.binds.MixinTickrateChangerAudioPitch",
		"render.binds.MixinTickrateChangerEnchantmentGlimm",
		"render.binds.MixinTickrateChangerSubtitleOverlay",
		"render.binds.MixinTickrateChangerWorldborder",
		"render.gui.MixinGuiIngameMenu",
		"render.gui.MixinGuiMainMenu",
		"render.gui.MixinGuiSelectWorldScreen",
		"render.MixinOverlayEvent",
		"render.MixinRenderEvent",
		"render.MixinPotionRenderer",
		"render.MixinRenderShield",
		"patches.MixinBlockPatch",
		"patches.MixinEntityPatch",
		"patches.MixinExplosionPatch",
		"patches.MixinServerPlayerEntityPatch",
		"patches.MixinEnderPearlPatch",
		"patches.MixinUnbreakingPatch",
		"patches.MixinIntegratedServerPatch",
		"patches.MixinEndPortalPatch",
		"patches.MixinItemEntity"
	],
  	"injectors": {
    	"defaultRequire": 1
  	}
}